pyintergraph/Graph.py
pyintergraph/__init__.py
pyintergraph/exceptions.py
pyintergraph/funcs.py
pyintergraph/infer.py
pyintergraph-1.3.3.dist-info/LICENSE
pyintergraph-1.3.3.dist-info/METADATA
pyintergraph-1.3.3.dist-info/WHEEL
pyintergraph-1.3.3.dist-info/RECORD
