Metadata-Version: 2.1
Name: pyintergraph
Version: 1.3.3
Summary: Convert Python-Graph-Objects between networkx, python-igraph and graph-tools.
Home-page: https://github.com/luerhard/pyintergraph
License: MIT
Author: Lukas Erhard
Author-email: luerhard@googlemail.com
Requires-Python: >=3.8,<4.0
Classifier: Intended Audience :: Science/Research
Classifier: License :: OSI Approved :: MIT License
Classifier: Programming Language :: Python :: 3
Classifier: Programming Language :: Python :: 3.8
Classifier: Programming Language :: Python :: 3.9
Classifier: Programming Language :: Python :: 3.10
Classifier: Programming Language :: Python :: 3.11
Classifier: Programming Language :: Python :: 3.12
Classifier: Topic :: Utilities
Provides-Extra: net
Provides-Extra: networkx
Provides-Extra: python-igraph
Requires-Dist: networkx (>=2.4) ; extra == "networkx" or extra == "net"
Requires-Dist: numpy (>=1.18) ; python_version < "3.12"
Requires-Dist: numpy (>=1.26) ; python_version >= "3.12"
Requires-Dist: python-igraph (>=0.8) ; extra == "python-igraph" or extra == "net"
Project-URL: Repository, https://github.com/luerhard/pyintergraph
